starkbank/__init__.py
starkbank/error.py
starkbank/key.py
starkbank/balance/__balance.py
starkbank/balance/__init__.py
starkbank/boleto/__boleto.py
starkbank/boleto/__init__.py
starkbank/boleto/log/__init__.py
starkbank/boleto/log/__log.py
starkbank/boletoholmes/__boletoholmes.py
starkbank/boletoholmes/__init__.py
starkbank/boletoholmes/log/__init__.py
starkbank/boletoholmes/log/__log.py
starkbank/boletopayment/__boletopayment.py
starkbank/boletopayment/__init__.py
starkbank/boletopayment/log/__init__.py
starkbank/boletopayment/log/__log.py
starkbank/brcodepayment/__brcodepayment.py
starkbank/brcodepayment/__init__.py
starkbank/brcodepayment/log/__init__.py
starkbank/brcodepayment/log/__log.py
starkbank/brcodepayment/rule/__init__.py
starkbank/brcodepayment/rule/__rule.py
starkbank/cardmethod/__cardmethod.py
starkbank/cardmethod/__init__.py
starkbank/corporatebalance/__corporatebalance.py
starkbank/corporatebalance/__init__.py
starkbank/corporatecard/__corporatecard.py
starkbank/corporatecard/__init__.py
starkbank/corporatecard/log/__init__.py
starkbank/corporatecard/log/__log.py
starkbank/corporateholder/__corporateholder.py
starkbank/corporateholder/__init__.py
starkbank/corporateholder/__permission.py
starkbank/corporateholder/log/__init__.py
starkbank/corporateholder/log/__log.py
starkbank/corporateinvoice/__corporateinvoice.py
starkbank/corporateinvoice/__init__.py
starkbank/corporatepurchase/__corporatepurchase.py
starkbank/corporatepurchase/__init__.py
starkbank/corporatepurchase/log/__init__.py
starkbank/corporatepurchase/log/__log.py
starkbank/corporaterule/__corporaterule.py
starkbank/corporaterule/__init__.py
starkbank/corporatetransaction/__corporatetransaction.py
starkbank/corporatetransaction/__init__.py
starkbank/corporatewithdrawal/__corporatewithdrawal.py
starkbank/corporatewithdrawal/__init__.py
starkbank/darfpayment/__darfpayment.py
starkbank/darfpayment/__init__.py
starkbank/darfpayment/log/__init__.py
starkbank/darfpayment/log/__log.py
starkbank-2.31.0.dist-info/LICENSE.txt
starkbank-2.31.0.dist-info/METADATA
starkbank-2.31.0.dist-info/WHEEL
starkbank-2.31.0.dist-info/top_level.txt
starkbank-2.31.0.dist-info/RECORD
