Metadata-Version: 2.1
Name: starkbank
Version: 2.31.0
Summary: SDK to facilitate Python integrations with Stark Bank
Home-page: https://github.com/starkbank/sdk-python
Author: Stark Bank
Author-email: developers@starkbank.com
License: MIT License
Keywords: stark bank,starkbank,sdk,open banking,openbanking,banking,open,stark
Platform: UNKNOWN
License-File: LICENSE.txt
Requires-Dist: starkcore >=0.0.5
